CHANGELOG.txt
COPYING.txt
MANIFEST.in
README.txt
setup.cfg
setup.py
docs/Makefile
docs/source/conf.py
docs/source/index.txt
docs/source/logo.jpg
docs/source/doc/README.txt
docs/source/doc/price.txt
docs/source/doc/rules.txt
docs/source/doc/rules_config.txt
docs/source/doc/standard_rules.txt
docs/source/doc/etc/rules.cfg
docs/source/modules/cart.txt
docs/source/modules/price.txt
docs/source/modules/rules.txt
docs/source/modules/rules_config.txt
docs/source/modules/standard_rules.txt
ecs/__init__.py
ecs.cart.egg-info/PKG-INFO
ecs.cart.egg-info/SOURCES.txt
ecs.cart.egg-info/dependency_links.txt
ecs.cart.egg-info/entry_points.txt
ecs.cart.egg-info/namespace_packages.txt
ecs.cart.egg-info/not-zip-safe
ecs.cart.egg-info/requires.txt
ecs.cart.egg-info/top_level.txt
ecs/cart/TODO.txt
ecs/cart/__init__.py
ecs/cart/cart.py
ecs/cart/price.py
ecs/cart/rules/__init__.py
ecs/cart/rules/rules.py
ecs/cart/rules/rules_config.py
ecs/cart/rules/standard_rules.py
ecs/cart/tests/__init__.py
ecs/cart/tests/__init__.py.old
ecs/cart/tests/test_cart.py
ecs/cart/tests/test_cart.py.old
ecs/cart/tests/test_rules.py
ecs/cart/tests/test_rules.py.old