Metadata-Version: 1.0
Name: ecs.cart
Version: 0.4dev-r2383
Summary: Package from the ecs suite, that provide a cart object for ecommerce projects
Home-page: http://emencia.com
Author: Lafaye Philippe
Author-email: lafaye@emencia.com
License: GPLv3
Keywords: ecs emencia e-commerce commerce shop cart e-shop
Platform: UNKNOWN
